xia_broadcast_fastapi/__init__.py
xia_broadcast_fastapi/broadcaster.cp310-win_amd64.pyd
xia_broadcast_fastapi-0.1.4.dist-info/LICENSE.txt
xia_broadcast_fastapi-0.1.4.dist-info/METADATA
xia_broadcast_fastapi-0.1.4.dist-info/WHEEL
xia_broadcast_fastapi-0.1.4.dist-info/top_level.txt
xia_broadcast_fastapi-0.1.4.dist-info/RECORD
