Metadata-Version: 2.1
Name: xia-broadcast-fastapi
Version: 0.1.4
Home-page: https://develop.x-i-a.com/docs/xia-broadcast-fastapi/0.1.4/index.html
Author: X-I-A
Author-email: admin@x-i-a.com
Requires-Python: >=3.9
License-File: LICENSE.txt
Requires-Dist: fastapi
Requires-Dist: xia-broadcast
Requires-Dist: xia-logger
